{"slideHeight":768,
"filename":"1 - Introduction",
"navigatorEvents":[{"eventName":"Slide 1",
"eventIndex":0}
,{"eventName":"Slide 2",
"eventIndex":1}
,{"eventName":"Slide 3",
"eventIndex":2}
,{"eventName":"Slide 4",
"eventIndex":3}
,{"eventName":"Slide 5",
"eventIndex":4}
,{"eventName":"Slide 6",
"eventIndex":5}
,{"eventName":"Slide 7",
"eventIndex":6}
,{"eventName":"Slide 8",
"eventIndex":7}
,{"eventName":"Slide 9",
"eventIndex":8}
,{"eventName":"Slide 10",
"eventIndex":9}
,{"eventName":"Slide 11",
"eventIndex":10}
,{"eventName":"Slide 12",
"eventIndex":11}
,{"eventName":"Slide 13",
"eventIndex":12}
,{"eventName":"Slide 14",
"eventIndex":13}
,{"eventName":"Slide 15",
"eventIndex":14}
,{"eventName":"Slide 16",
"eventIndex":15}
,{"eventName":"Slide 17",
"eventIndex":16}
,{"eventName":"Slide 18",
"eventIndex":17}
,{"eventName":"Slide 19",
"eventIndex":18}
,{"eventName":"Slide 20",
"eventIndex":19}
,{"eventName":"Slide 21",
"eventIndex":20}
,{"eventName":"Slide 22",
"eventIndex":21}
,{"eventName":"Slide 23",
"eventIndex":22}
,{"eventName":"Slide 24",
"eventIndex":23}
,{"eventName":"Slide 25",
"eventIndex":24}
,{"eventName":"Slide 26",
"eventIndex":25}
,{"eventName":"Slide 27",
"eventIndex":26}
,{"eventName":"Slide 28",
"eventIndex":27}
,{"eventName":"Slide 29",
"eventIndex":28}
]
,
"textures":{"thumbnail":{"url":"images-1/thumbnail.jpeg",
"width":458,
"height":344}
,
"s1.b":{"url":"images-1/s1.b.jpeg",
"width":1024,
"height":768}
,
"s6.b":{"url":"images-1/s6.b.jpeg",
"width":1024,
"height":768}
,
"s2.a":{"url":"images-1/s1.b.jpeg",
"width":1024,
"height":768}
,
"s11.b":{"url":"images-1/s11.b.jpeg",
"width":1024,
"height":768}
,
"s7.a":{"url":"images-1/s6.b.jpeg",
"width":1024,
"height":768}
,
"s14.b":{"url":"images-1/s14.b.jpeg",
"width":1024,
"height":768}
,
"s21.b":{"url":"images-1/s21.b.jpeg",
"width":1024,
"height":768}
,
"s17.b":{"url":"images-1/s17.b.jpeg",
"width":1024,
"height":768}
,
"s24.b":{"url":"images-1/s24.b.jpeg",
"width":1024,
"height":768}
,
"s27.b":{"url":"images-1/s27.b.jpeg",
"width":1024,
"height":768}
,
"s12.a":{"url":"images-1/s11.b.jpeg",
"width":1024,
"height":768}
,
"s15.a":{"url":"images-1/s14.b.jpeg",
"width":1024,
"height":768}
,
"s22.a":{"url":"images-1/s21.b.jpeg",
"width":1024,
"height":768}
,
"s18.a":{"url":"images-1/s17.b.jpeg",
"width":1024,
"height":768}
,
"s2.b":{"url":"images-1/s2.b.jpeg",
"width":1024,
"height":768}
,
"s25.a":{"url":"images-1/s24.b.jpeg",
"width":1024,
"height":768}
,
"s28.a":{"url":"images-1/s27.b.jpeg",
"width":1024,
"height":768}
,
"s7.b":{"url":"images-1/s7.b.jpeg",
"width":1024,
"height":768}
,
"s3.a":{"url":"images-1/s2.b.jpeg",
"width":1024,
"height":768}
,
"s8.a":{"url":"images-1/s7.b.jpeg",
"width":1024,
"height":768}
,
"s3.b":{"url":"images-1/s3.b.jpeg",
"width":1024,
"height":768}
,
"s12.b":{"url":"images-1/s12.b.jpeg",
"width":1024,
"height":768}
,
"s8.b":{"url":"images-1/s8.b.jpeg",
"width":1024,
"height":768}
,
"s15.b":{"url":"images-1/s15.b.jpeg",
"width":1024,
"height":768}
,
"s22.b":{"url":"images-1/s22.b.jpeg",
"width":1024,
"height":768}
,
"s18.b":{"url":"images-1/s18.b.jpeg",
"width":1024,
"height":768}
,
"s25.b":{"url":"images-1/s25.b.jpeg",
"width":1024,
"height":768}
,
"s28.b":{"url":"images-1/s28.b.jpeg",
"width":1024,
"height":768}
,
"s4.a":{"url":"images-1/s3.b.jpeg",
"width":1024,
"height":768}
,
"s10.a":{"url":"images-1/s9.b.jpeg",
"width":1024,
"height":768}
,
"s9.a":{"url":"images-1/s8.b.jpeg",
"width":1024,
"height":768}
,
"s13.a":{"url":"images-1/s12.b.jpeg",
"width":1024,
"height":768}
,
"s16.a":{"url":"images-1/s15.b.jpeg",
"width":1024,
"height":768}
,
"s23.a":{"url":"images-1/s22.b.jpeg",
"width":1024,
"height":768}
,
"s19.a":{"url":"images-1/s18.b.jpeg",
"width":1024,
"height":768}
,
"s20.a":{"url":"images-1/s19.b.jpeg",
"width":1024,
"height":768}
,
"s26.a":{"url":"images-1/s25.b.jpeg",
"width":1024,
"height":768}
,
"s29.a":{"url":"images-1/s28.b.jpeg",
"width":1024,
"height":768}
,
"s4.b":{"url":"images-1/s4.b.jpeg",
"width":1024,
"height":768}
,
"s9.b":{"url":"images-1/s9.b.jpeg",
"width":1024,
"height":768}
,
"s5.a":{"url":"images-1/s4.b.jpeg",
"width":1024,
"height":768}
,
"s10.b":{"url":"images-1/s10.b.jpeg",
"width":1024,
"height":768}
,
"s13.b":{"url":"images-1/s13.b.jpeg",
"width":1024,
"height":768}
,
"s20.b":{"url":"images-1/s20.b.jpeg",
"width":1024,
"height":768}
,
"s16.b":{"url":"images-1/s16.b.jpeg",
"width":1024,
"height":768}
,
"s23.b":{"url":"images-1/s23.b.jpeg",
"width":1024,
"height":768}
,
"s19.b":{"url":"images-1/s19.b.jpeg",
"width":1024,
"height":768}
,
"s26.b":{"url":"images-1/s26.b.jpeg",
"width":1024,
"height":768}
,
"s29.b":{"url":"images-1/s29.b.png",
"width":1024,
"height":768}
,
"s5.b":{"url":"images-1/s5.b.jpeg",
"width":1024,
"height":768}
,
"s11.a":{"url":"images-1/s10.b.jpeg",
"width":1024,
"height":768}
,
"s14.a":{"url":"images-1/s13.b.jpeg",
"width":1024,
"height":768}
,
"s21.a":{"url":"images-1/s20.b.jpeg",
"width":1024,
"height":768}
,
"s17.a":{"url":"images-1/s16.b.jpeg",
"width":1024,
"height":768}
,
"s1.a":{"url":"images-1/s1.a.jpeg",
"width":1024,
"height":768}
,
"s24.a":{"url":"images-1/s23.b.jpeg",
"width":1024,
"height":768}
,
"s27.a":{"url":"images-1/s26.b.jpeg",
"width":1024,
"height":768}
,
"s6.a":{"url":"images-1/s5.b.jpeg",
"width":1024,
"height":768}
}
,
"title":"1 - Introduction",
"minorVersion":4,
"timestamp":"2013-01-14 22:15:49",
"slideWidth":1024,
"eventTimelines":[{"automaticPlay":false,
"hyperlinks":[]
,
"eventInitialStates":[{"opacity":1,
"affineTransform":[1,0,0,1,0,0]
,
"texture":"s1.b",
"hidden":0}
,{"opacity":1,
"affineTransform":[1,0,0,1,0,0]
,
"texture":"s1.a",
"hidden":0}
]
,
"eventAnimations":[{"effect":"none",
"actions":[{"beginTime":0,
"from":{"scalar":1}
,
"action":"hidden",
"texture":"s1.a",
"to":{"scalar":1}
,
"timingFunction":"linear",
"duration":0.001}
]
,
"duration":0.001,
"animationType":"transition",
"beginTime":0,
"textures":["s1.a"]
}
,{"effect":"none",
"actions":[{"beginTime":0,
"from":{"scalar":0}
,
"action":"hidden",
"texture":"s1.b",
"to":{"scalar":0}
,
"timingFunction":"linear",
"duration":0.001}
]
,
"duration":0.001,
"animationType":"transition",
"beginTime":0,
"textures":["s1.b"]
}
]
,
"textRegions":[{"targetRectangle":{"y":203,
"width":810,
"x":107,
"height":182}
,
"text":"Introduction to Programming Concepts"}
,{"targetRectangle":{"y":400,
"width":164,
"x":430,
"height":38}
,
"text":"Ryan Nixon"}
]
}
,{"automaticPlay":false,
"hyperlinks":[]
,
"eventInitialStates":[{"opacity":1,
"affineTransform":[1,0,0,1,0,0]
,
"texture":"s2.b",
"hidden":0}
,{"opacity":1,
"affineTransform":[1,0,0,1,0,0]
,
"texture":"s2.a",
"hidden":0}
]
,
"eventAnimations":[{"effect":"none",
"actions":[{"beginTime":0,
"from":{"scalar":1}
,
"action":"hidden",
"texture":"s2.a",
"to":{"scalar":1}
,
"timingFunction":"linear",
"duration":0.001}
]
,
"duration":0.001,
"animationType":"transition",
"beginTime":0,
"textures":["s2.a"]
}
,{"effect":"none",
"actions":[{"beginTime":0,
"from":{"scalar":0}
,
"action":"hidden",
"texture":"s2.b",
"to":{"scalar":0}
,
"timingFunction":"linear",
"duration":0.001}
]
,
"duration":0.001,
"animationType":"transition",
"beginTime":0,
"textures":["s2.b"]
}
]
,
"textRegions":[{"targetRectangle":{"y":70,
"width":812,
"x":106,
"height":92}
,
"text":"History of Programming"}
,{"targetRectangle":{"y":284,
"width":773,
"x":134,
"height":180}
,
"text":"Programming has ties all the way back to the 18th century and has undergone many transformations"}
,{"targetRectangle":{"y":464,
"width":700,
"x":134,
"height":138}
,
"text":"Here is a very brief history of computing, summarized through the people that contributed to the advancements"}
]
}
,{"automaticPlay":false,
"hyperlinks":[]
,
"eventInitialStates":[{"opacity":1,
"affineTransform":[1,0,0,1,0,0]
,
"texture":"s3.b",
"hidden":0}
,{"opacity":1,
"affineTransform":[1,0,0,1,0,0]
,
"texture":"s3.a",
"hidden":0}
]
,
"eventAnimations":[{"effect":"none",
"actions":[{"beginTime":0,
"from":{"scalar":1}
,
"action":"hidden",
"texture":"s3.a",
"to":{"scalar":1}
,
"timingFunction":"linear",
"duration":0.001}
]
,
"duration":0.001,
"animationType":"transition",
"beginTime":0,
"textures":["s3.a"]
}
,{"effect":"none",
"actions":[{"beginTime":0,
"from":{"scalar":0}
,
"action":"hidden",
"texture":"s3.b",
"to":{"scalar":0}
,
"timingFunction":"linear",
"duration":0.001}
]
,
"duration":0.001,
"animationType":"transition",
"beginTime":0,
"textures":["s3.b"]
}
]
,
"textRegions":[{"targetRectangle":{"y":68,
"width":794,
"x":115,
"height":96}
,
"text":"The Difference Engine"}
,{"targetRectangle":{"y":223,
"width":279,
"x":127,
"height":49}
,
"text":"Charles Babbage (1791-1871)"}
,{"targetRectangle":{"y":271,
"width":324,
"x":157,
"height":74}
,
"text":"Making a difference...engine. Then designs for the analytical engine."}
,{"targetRectangle":{"y":344,
"width":294,
"x":157,
"height":125}
,
"text":"Developed the first “computer”, more a simple calculator but signaled the beginnings of computing"}
,{"targetRectangle":{"y":468,
"width":244,
"x":127,
"height":49}
,
"text":"Ada Lovelace (1815-1852)"}
,{"targetRectangle":{"y":516,
"width":282,
"x":157,
"height":49}
,
"text":"“The Enchantress of Numbers”"}
,{"targetRectangle":{"y":564,
"width":318,
"x":157,
"height":75}
,
"text":"Collaborated with Babbage on his designs"}
,{"targetRectangle":{"y":638,
"width":299,
"x":157,
"height":26}
,
"text":"Considered the first Programmer"}
]
}
,{"automaticPlay":false,
"hyperlinks":[]
,
"eventInitialStates":[{"opacity":1,
"affineTransform":[1,0,0,1,0,0]
,
"texture":"s4.b",
"hidden":0}
,{"opacity":1,
"affineTransform":[1,0,0,1,0,0]
,
"texture":"s4.a",
"hidden":0}
]
,
"eventAnimations":[{"effect":"none",
"actions":[{"beginTime":0,
"from":{"scalar":1}
,
"action":"hidden",
"texture":"s4.a",
"to":{"scalar":1}
,
"timingFunction":"linear",
"duration":0.001}
]
,
"duration":0.001,
"animationType":"transition",
"beginTime":0,
"textures":["s4.a"]
}
,{"effect":"none",
"actions":[{"beginTime":0,
"from":{"scalar":0}
,
"action":"hidden",
"texture":"s4.b",
"to":{"scalar":0}
,
"timingFunction":"linear",
"duration":0.001}
]
,
"duration":0.001,
"animationType":"transition",
"beginTime":0,
"textures":["s4.b"]
}
]
,
"textRegions":[{"targetRectangle":{"y":24,
"width":642,
"x":191,
"height":184}
,
"text":"The Founding of Computer Science"}
,{"targetRectangle":{"y":234,
"width":256,
"x":127,
"height":56}
,
"text":"Alan Turing (1912-1954)"}
,{"targetRectangle":{"y":289,
"width":273,
"x":157,
"height":84}
,
"text":"Developed the ideas for computation & algorithms"}
,{"targetRectangle":{"y":372,
"width":329,
"x":157,
"height":112}
,
"text":"Created the “Turing Machine”, a hypothetical device capable of executing any program"}
,{"targetRectangle":{"y":483,
"width":337,
"x":157,
"height":169}
,
"text":"Advanced artificial intelligence forward with the “Turing Test”, a proctored exam between a machine and human to determine believability of the program"}
]
}
,{"automaticPlay":false,
"hyperlinks":[]
,
"eventInitialStates":[{"opacity":1,
"affineTransform":[1,0,0,1,0,0]
,
"texture":"s5.b",
"hidden":0}
,{"opacity":1,
"affineTransform":[1,0,0,1,0,0]
,
"texture":"s5.a",
"hidden":0}
]
,
"eventAnimations":[{"effect":"none",
"actions":[{"beginTime":0,
"from":{"scalar":1}
,
"action":"hidden",
"texture":"s5.a",
"to":{"scalar":1}
,
"timingFunction":"linear",
"duration":0.001}
]
,
"duration":0.001,
"animationType":"transition",
"beginTime":0,
"textures":["s5.a"]
}
,{"effect":"none",
"actions":[{"beginTime":0,
"from":{"scalar":0}
,
"action":"hidden",
"texture":"s5.b",
"to":{"scalar":0}
,
"timingFunction":"linear",
"duration":0.001}
]
,
"duration":0.001,
"animationType":"transition",
"beginTime":0,
"textures":["s5.b"]
}
]
,
"textRegions":[{"targetRectangle":{"y":24,
"width":446,
"x":300,
"height":184}
,
"text":"Modern Day Computers"}
,{"targetRectangle":{"y":228,
"width":367,
"x":127,
"height":61}
,
"text":"John von Neumann (1903-1957)"}
,{"targetRectangle":{"y":288,
"width":367,
"x":127,
"height":216}
,
"text":"Pioneered the \"Von Neumann\" model, a modern day computing architecture wherein the processing, arithmetic operations, memory and storage were separate"}
,{"targetRectangle":{"y":503,
"width":367,
"x":127,
"height":156}
,
"text":"This model allowed for machines to be built that stored programs on disk, rather than having to be redesigned for each task"}
]
}
,{"automaticPlay":false,
"hyperlinks":[]
,
"eventInitialStates":[{"opacity":1,
"affineTransform":[1,0,0,1,0,0]
,
"texture":"s6.b",
"hidden":0}
,{"opacity":1,
"affineTransform":[1,0,0,1,0,0]
,
"texture":"s6.a",
"hidden":0}
]
,
"eventAnimations":[{"effect":"none",
"actions":[{"beginTime":0,
"from":{"scalar":1}
,
"action":"hidden",
"texture":"s6.a",
"to":{"scalar":1}
,
"timingFunction":"linear",
"duration":0.001}
]
,
"duration":0.001,
"animationType":"transition",
"beginTime":0,
"textures":["s6.a"]
}
,{"effect":"none",
"actions":[{"beginTime":0,
"from":{"scalar":0}
,
"action":"hidden",
"texture":"s6.b",
"to":{"scalar":0}
,
"timingFunction":"linear",
"duration":0.001}
]
,
"duration":0.001,
"animationType":"transition",
"beginTime":0,
"textures":["s6.b"]
}
]
,
"textRegions":[{"targetRectangle":{"y":68,
"width":188,
"x":418,
"height":96}
,
"text":"Bugs"}
,{"targetRectangle":{"y":234,
"width":229,
"x":127,
"height":56}
,
"text":"Grace Hopper (1947)"}
,{"targetRectangle":{"y":289,
"width":355,
"x":127,
"height":112}
,
"text":"Removed a moth from one of the first computers (the Mark II), called it a “bug”"}
,{"targetRectangle":{"y":400,
"width":357,
"x":127,
"height":168}
,
"text":"Hopper then popularized the term, resulting in modern-day computer programs having bugs when something goes wrong in their programming"}
,{"targetRectangle":{"y":567,
"width":362,
"x":127,
"height":85}
,
"text":"“Debugging” would be the action of sleuthing out and removing these bugs"}
]
}
,{"automaticPlay":false,
"hyperlinks":[]
,
"eventInitialStates":[{"opacity":1,
"affineTransform":[1,0,0,1,0,0]
,
"texture":"s7.b",
"hidden":0}
,{"opacity":1,
"affineTransform":[1,0,0,1,0,0]
,
"texture":"s7.a",
"hidden":0}
]
,
"eventAnimations":[{"effect":"none",
"actions":[{"beginTime":0,
"from":{"scalar":1}
,
"action":"hidden",
"texture":"s7.a",
"to":{"scalar":1}
,
"timingFunction":"linear",
"duration":0.001}
]
,
"duration":0.001,
"animationType":"transition",
"beginTime":0,
"textures":["s7.a"]
}
,{"effect":"none",
"actions":[{"beginTime":0,
"from":{"scalar":0}
,
"action":"hidden",
"texture":"s7.b",
"to":{"scalar":0}
,
"timingFunction":"linear",
"duration":0.001}
]
,
"duration":0.001,
"animationType":"transition",
"beginTime":0,
"textures":["s7.b"]
}
]
,
"textRegions":[{"targetRectangle":{"y":68,
"width":730,
"x":147,
"height":96}
,
"text":"Personal Computers"}
,{"targetRectangle":{"y":241,
"width":367,
"x":127,
"height":100}
,
"text":"Steve Jobs & Steve Wozniak, Apple Computer (1976)"}
,{"targetRectangle":{"y":341,
"width":319,
"x":127,
"height":168}
,
"text":"Moved the computer era from mainframes and business machines to computers in every home"}
,{"targetRectangle":{"y":509,
"width":364,
"x":127,
"height":136}
,
"text":"Greatly expanded the software market, creating an explosion of programmer jobs"}
]
}
,{"automaticPlay":false,
"hyperlinks":[]
,
"eventInitialStates":[{"opacity":1,
"affineTransform":[1,0,0,1,0,0]
,
"texture":"s8.b",
"hidden":0}
,{"opacity":1,
"affineTransform":[1,0,0,1,0,0]
,
"texture":"s8.a",
"hidden":0}
]
,
"eventAnimations":[{"effect":"none",
"actions":[{"beginTime":0,
"from":{"scalar":1}
,
"action":"hidden",
"texture":"s8.a",
"to":{"scalar":1}
,
"timingFunction":"linear",
"duration":0.001}
]
,
"duration":0.001,
"animationType":"transition",
"beginTime":0,
"textures":["s8.a"]
}
,{"effect":"none",
"actions":[{"beginTime":0,
"from":{"scalar":0}
,
"action":"hidden",
"texture":"s8.b",
"to":{"scalar":0}
,
"timingFunction":"linear",
"duration":0.001}
]
,
"duration":0.001,
"animationType":"transition",
"beginTime":0,
"textures":["s8.b"]
}
]
,
"textRegions":[{"targetRectangle":{"y":24,
"width":655,
"x":195,
"height":184}
,
"text":"Modern Operating Systems"}
,{"targetRectangle":{"y":225,
"width":295,
"x":127,
"height":100}
,
"text":"Bill Gates & Paul Allen, Microsoft (1975)"}
,{"targetRectangle":{"y":325,
"width":357,
"x":127,
"height":134}
,
"text":"Developed the Windows platform and freely licensed it to PC manufacturers"}
,{"targetRectangle":{"y":459,
"width":275,
"x":127,
"height":100}
,
"text":"The first real software powerhouse"}
,{"targetRectangle":{"y":559,
"width":339,
"x":127,
"height":102}
,
"text":"Continues to advance the software industry 30 years later with the .NET platform"}
]
}
,{"automaticPlay":false,
"hyperlinks":[]
,
"eventInitialStates":[{"opacity":1,
"affineTransform":[1,0,0,1,0,0]
,
"texture":"s9.b",
"hidden":0}
,{"opacity":1,
"affineTransform":[1,0,0,1,0,0]
,
"texture":"s9.a",
"hidden":0}
]
,
"eventAnimations":[{"effect":"none",
"actions":[{"beginTime":0,
"from":{"scalar":1}
,
"action":"hidden",
"texture":"s9.a",
"to":{"scalar":1}
,
"timingFunction":"linear",
"duration":0.001}
]
,
"duration":0.001,
"animationType":"transition",
"beginTime":0,
"textures":["s9.a"]
}
,{"effect":"none",
"actions":[{"beginTime":0,
"from":{"scalar":0}
,
"action":"hidden",
"texture":"s9.b",
"to":{"scalar":0}
,
"timingFunction":"linear",
"duration":0.001}
]
,
"duration":0.001,
"animationType":"transition",
"beginTime":0,
"textures":["s9.b"]
}
]
,
"textRegions":[{"targetRectangle":{"y":68,
"width":598,
"x":213,
"height":96}
,
"text":"World Wide Web"}
,{"targetRectangle":{"y":227,
"width":282,
"x":127,
"height":62}
,
"text":"Tim Berners-Lee (1990)"}
,{"targetRectangle":{"y":288,
"width":344,
"x":127,
"height":186}
,
"text":"Created the WorldWideWeb browser and HTTPd web server which spawned the world wide web that we now take for granted"}
,{"targetRectangle":{"y":473,
"width":367,
"x":127,
"height":187}
,
"text":"Single-handledly created the web development industry that uses web servers and the HTTP protocol rather than building specifically against the computer"}
]
}
,{"automaticPlay":false,
"hyperlinks":[]
,
"eventInitialStates":[{"opacity":1,
"affineTransform":[1,0,0,1,0,0]
,
"texture":"s10.b",
"hidden":0}
,{"opacity":1,
"affineTransform":[1,0,0,1,0,0]
,
"texture":"s10.a",
"hidden":0}
]
,
"eventAnimations":[{"effect":"none",
"actions":[{"beginTime":0,
"from":{"scalar":1}
,
"action":"hidden",
"texture":"s10.a",
"to":{"scalar":1}
,
"timingFunction":"linear",
"duration":0.001}
]
,
"duration":0.001,
"animationType":"transition",
"beginTime":0,
"textures":["s10.a"]
}
,{"effect":"none",
"actions":[{"beginTime":0,
"from":{"scalar":0}
,
"action":"hidden",
"texture":"s10.b",
"to":{"scalar":0}
,
"timingFunction":"linear",
"duration":0.001}
]
,
"duration":0.001,
"animationType":"transition",
"beginTime":0,
"textures":["s10.b"]
}
]
,
"textRegions":[{"targetRectangle":{"y":68,
"width":708,
"x":158,
"height":96}
,
"text":"The Virtual Machine"}
,{"targetRectangle":{"y":235,
"width":356,
"x":127,
"height":78}
,
"text":"James Gosling, Sun Microsystems (1991)"}
,{"targetRectangle":{"y":312,
"width":353,
"x":127,
"height":105}
,
"text":"Developed the Java programming language as a “write-once, run anywhere” system"}
,{"targetRectangle":{"y":416,
"width":353,
"x":127,
"height":157}
,
"text":"Created the concept of the Java Virtual Machine, an abstract machine that sits between the program and the real hardware, to achieve this mobility"}
,{"targetRectangle":{"y":572,
"width":354,
"x":127,
"height":79}
,
"text":"Led to the Microsoft .NET platform which also runs on a virtual machine"}
]
}
,{"automaticPlay":false,
"hyperlinks":[]
,
"eventInitialStates":[{"opacity":1,
"affineTransform":[1,0,0,1,0,0]
,
"texture":"s11.b",
"hidden":0}
,{"opacity":1,
"affineTransform":[1,0,0,1,0,0]
,
"texture":"s11.a",
"hidden":0}
]
,
"eventAnimations":[{"effect":"none",
"actions":[{"beginTime":0,
"from":{"scalar":1}
,
"action":"hidden",
"texture":"s11.a",
"to":{"scalar":1}
,
"timingFunction":"linear",
"duration":0.001}
]
,
"duration":0.001,
"animationType":"transition",
"beginTime":0,
"textures":["s11.a"]
}
,{"effect":"none",
"actions":[{"beginTime":0,
"from":{"scalar":0}
,
"action":"hidden",
"texture":"s11.b",
"to":{"scalar":0}
,
"timingFunction":"linear",
"duration":0.001}
]
,
"duration":0.001,
"animationType":"transition",
"beginTime":0,
"textures":["s11.b"]
}
]
,
"textRegions":[{"targetRectangle":{"y":68,
"width":484,
"x":270,
"height":96}
,
"text":"Programmers"}
,{"targetRectangle":{"y":397,
"width":733,
"x":166,
"height":93}
,
"text":"Q: How many programmers does it take to plug in a light bulb?"}
]
}
,{"automaticPlay":false,
"hyperlinks":[]
,
"eventInitialStates":[{"opacity":1,
"affineTransform":[1,0,0,1,0,0]
,
"texture":"s12.b",
"hidden":0}
,{"opacity":1,
"affineTransform":[1,0,0,1,0,0]
,
"texture":"s12.a",
"hidden":0}
]
,
"eventAnimations":[{"effect":"none",
"actions":[{"beginTime":0,
"from":{"scalar":1}
,
"action":"hidden",
"texture":"s12.a",
"to":{"scalar":1}
,
"timingFunction":"linear",
"duration":0.001}
]
,
"duration":0.001,
"animationType":"transition",
"beginTime":0,
"textures":["s12.a"]
}
,{"effect":"none",
"actions":[{"beginTime":0,
"from":{"scalar":0}
,
"action":"hidden",
"texture":"s12.b",
"to":{"scalar":0}
,
"timingFunction":"linear",
"duration":0.001}
]
,
"duration":0.001,
"animationType":"transition",
"beginTime":0,
"textures":["s12.b"]
}
]
,
"textRegions":[{"targetRectangle":{"y":68,
"width":484,
"x":270,
"height":96}
,
"text":"Programmers"}
,{"targetRectangle":{"y":420,
"width":610,
"x":222,
"height":47}
,
"text":"A: Sorry, that’s a hardware problem."}
]
}
,{"automaticPlay":false,
"hyperlinks":[]
,
"eventInitialStates":[{"opacity":1,
"affineTransform":[1,0,0,1,0,0]
,
"texture":"s13.b",
"hidden":0}
,{"opacity":1,
"affineTransform":[1,0,0,1,0,0]
,
"texture":"s13.a",
"hidden":0}
]
,
"eventAnimations":[{"effect":"none",
"actions":[{"beginTime":0,
"from":{"scalar":1}
,
"action":"hidden",
"texture":"s13.a",
"to":{"scalar":1}
,
"timingFunction":"linear",
"duration":0.001}
]
,
"duration":0.001,
"animationType":"transition",
"beginTime":0,
"textures":["s13.a"]
}
,{"effect":"none",
"actions":[{"beginTime":0,
"from":{"scalar":0}
,
"action":"hidden",
"texture":"s13.b",
"to":{"scalar":0}
,
"timingFunction":"linear",
"duration":0.001}
]
,
"duration":0.001,
"animationType":"transition",
"beginTime":0,
"textures":["s13.b"]
}
]
,
"textRegions":[{"targetRectangle":{"y":68,
"width":484,
"x":270,
"height":96}
,
"text":"Programmers"}
,{"targetRectangle":{"y":218,
"width":0,
"x":101,
"height":0}
,
"text":""}
,{"targetRectangle":{"y":273,
"width":367,
"x":127,
"height":157}
,
"text":"Programmers use a machine language to instruct a computer what to do. This may include writing a program that tells another program what to do"}
,{"targetRectangle":{"y":429,
"width":356,
"x":127,
"height":157}
,
"text":"They need to be aware of how a machine works and how to work with peripherals, but the magic happens only while the machine is running"}
,{"targetRectangle":{"y":585,
"width":358,
"x":127,
"height":79}
,
"text":"Note that programmers come in all types, scripters, web developers, kernel junkies. To each your own"}
]
}
,{"automaticPlay":false,
"hyperlinks":[]
,
"eventInitialStates":[{"opacity":1,
"affineTransform":[1,0,0,1,0,0]
,
"texture":"s14.b",
"hidden":0}
,{"opacity":1,
"affineTransform":[1,0,0,1,0,0]
,
"texture":"s14.a",
"hidden":0}
]
,
"eventAnimations":[{"effect":"none",
"actions":[{"beginTime":0,
"from":{"scalar":1}
,
"action":"hidden",
"texture":"s14.a",
"to":{"scalar":1}
,
"timingFunction":"linear",
"duration":0.001}
]
,
"duration":0.001,
"animationType":"transition",
"beginTime":0,
"textures":["s14.a"]
}
,{"effect":"none",
"actions":[{"beginTime":0,
"from":{"scalar":0}
,
"action":"hidden",
"texture":"s14.b",
"to":{"scalar":0}
,
"timingFunction":"linear",
"duration":0.001}
]
,
"duration":0.001,
"animationType":"transition",
"beginTime":0,
"textures":["s14.b"]
}
]
,
"textRegions":[{"targetRectangle":{"y":68,
"width":694,
"x":165,
"height":96}
,
"text":"Machine Language"}
,{"targetRectangle":{"y":224,
"width":725,
"x":134,
"height":88}
,
"text":"The real programming language, used by computers to process instructions and to communicate with other computers"}
,{"targetRectangle":{"y":311,
"width":747,
"x":134,
"height":89}
,
"text":"Consists of binary numbers - a base 2 numbering system used by computers"}
,{"targetRectangle":{"y":399,
"width":783,
"x":134,
"height":59}
,
"text":"Bit - 0 or 1. This may also be considered on/off, true/false, yes/no, etc."}
,{"targetRectangle":{"y":457,
"width":270,
"x":134,
"height":58}
,
"text":"Byte - 8 bits (01100100)"}
,{"targetRectangle":{"y":514,
"width":752,
"x":134,
"height":89}
,
"text":"These machine languages are specific to the architecture that is in use. AMD, Intel, Atom, etc. all have different instruction sets"}
,{"targetRectangle":{"y":602,
"width":781,
"x":134,
"height":61}
,
"text":"Near impossible to program. Programming languages are developed to assist with this"}
]
}
,{"automaticPlay":false,
"hyperlinks":[]
,
"eventInitialStates":[{"opacity":1,
"affineTransform":[1,0,0,1,0,0]
,
"texture":"s15.b",
"hidden":0}
,{"opacity":1,
"affineTransform":[1,0,0,1,0,0]
,
"texture":"s15.a",
"hidden":0}
]
,
"eventAnimations":[{"effect":"none",
"actions":[{"beginTime":0,
"from":{"scalar":1}
,
"action":"hidden",
"texture":"s15.a",
"to":{"scalar":1}
,
"timingFunction":"linear",
"duration":0.001}
]
,
"duration":0.001,
"animationType":"transition",
"beginTime":0,
"textures":["s15.a"]
}
,{"effect":"none",
"actions":[{"beginTime":0,
"from":{"scalar":0}
,
"action":"hidden",
"texture":"s15.b",
"to":{"scalar":0}
,
"timingFunction":"linear",
"duration":0.001}
]
,
"duration":0.001,
"animationType":"transition",
"beginTime":0,
"textures":["s15.b"]
}
]
,
"textRegions":[{"targetRectangle":{"y":68,
"width":788,
"x":118,
"height":96}
,
"text":"Low Level Languages"}
,{"targetRectangle":{"y":225,
"width":773,
"x":134,
"height":95}
,
"text":"Symbolic languages that directly represent instructions on the machine"}
,{"targetRectangle":{"y":319,
"width":317,
"x":134,
"height":152}
,
"text":"LW\t $t0,\t4($gp)\u2028ADD\t $t1,\t$t0,\t3\u2028MULT $t1,\t$t1,\t$t0\u2028SW\t $t1,\t0($gp)"}
,{"targetRectangle":{"y":470,
"width":779,
"x":134,
"height":127}
,
"text":"Programmers still need to know how to work with registers, the specifics of the processor implementations, and each vendor-specific instruction set"}
,{"targetRectangle":{"y":596,
"width":770,
"x":134,
"height":65}
,
"text":"Assembly (ASM) is the most common low-level language with many architecture-specific derivatives"}
]
}
,{"automaticPlay":false,
"hyperlinks":[]
,
"eventInitialStates":[{"opacity":1,
"affineTransform":[1,0,0,1,0,0]
,
"texture":"s16.b",
"hidden":0}
,{"opacity":1,
"affineTransform":[1,0,0,1,0,0]
,
"texture":"s16.a",
"hidden":0}
]
,
"eventAnimations":[{"effect":"none",
"actions":[{"beginTime":0,
"from":{"scalar":1}
,
"action":"hidden",
"texture":"s16.a",
"to":{"scalar":1}
,
"timingFunction":"linear",
"duration":0.001}
]
,
"duration":0.001,
"animationType":"transition",
"beginTime":0,
"textures":["s16.a"]
}
,{"effect":"none",
"actions":[{"beginTime":0,
"from":{"scalar":0}
,
"action":"hidden",
"texture":"s16.b",
"to":{"scalar":0}
,
"timingFunction":"linear",
"duration":0.001}
]
,
"duration":0.001,
"animationType":"transition",
"beginTime":0,
"textures":["s16.b"]
}
]
,
"textRegions":[{"targetRectangle":{"y":68,
"width":810,
"x":107,
"height":96}
,
"text":"High Level Languages"}
,{"targetRectangle":{"y":227,
"width":663,
"x":164,
"height":58}
,
"text":"Uses plain English to represent large groups of instructions"}
,{"targetRectangle":{"y":284,
"width":314,
"x":164,
"height":110}
,
"text":"int t0;\u2028cin >> t0;\u2028cout << t0 * (t0 + 3);"}
,{"targetRectangle":{"y":393,
"width":613,
"x":164,
"height":89}
,
"text":"Enables programmers to organize code in much more understandable ways"}
,{"targetRectangle":{"y":481,
"width":746,
"x":164,
"height":88}
,
"text":"Cannot be run directly on the machine. High level languages use compiler programs to convert understandable code to lower levels"}
,{"targetRectangle":{"y":568,
"width":756,
"x":164,
"height":91}
,
"text":"Interpreters are a type of compiler that compiles chunks of code as they are encountered while running. This is known as Just In Time (JIT) compiling"}
]
}
,{"automaticPlay":false,
"hyperlinks":[]
,
"eventInitialStates":[{"opacity":1,
"affineTransform":[1,0,0,1,0,0]
,
"texture":"s17.b",
"hidden":0}
,{"opacity":1,
"affineTransform":[1,0,0,1,0,0]
,
"texture":"s17.a",
"hidden":0}
]
,
"eventAnimations":[{"effect":"none",
"actions":[{"beginTime":0,
"from":{"scalar":1}
,
"action":"hidden",
"texture":"s17.a",
"to":{"scalar":1}
,
"timingFunction":"linear",
"duration":0.001}
]
,
"duration":0.001,
"animationType":"transition",
"beginTime":0,
"textures":["s17.a"]
}
,{"effect":"none",
"actions":[{"beginTime":0,
"from":{"scalar":0}
,
"action":"hidden",
"texture":"s17.b",
"to":{"scalar":0}
,
"timingFunction":"linear",
"duration":0.001}
]
,
"duration":0.001,
"animationType":"transition",
"beginTime":0,
"textures":["s17.b"]
}
]
,
"textRegions":[{"targetRectangle":{"y":68,
"width":810,
"x":107,
"height":96}
,
"text":"High Level Languages"}
,{"targetRectangle":{"y":227,
"width":703,
"x":164,
"height":157}
,
"text":"A third type of compiler does not compile to the machine language but to an intermediate language, (sometimes known as bytecode)"}
,{"targetRectangle":{"y":383,
"width":674,
"x":164,
"height":157}
,
"text":"Java uses this type. Java code is compiled to bytecode to be executed on the Java Virtual Machine (JVM)"}
,{"targetRectangle":{"y":539,
"width":756,
"x":164,
"height":121}
,
"text":"This allows Java code to be compiled once and run anywhere, on anything...phones, websites (using Applets), even your microwave if it has the JVM"}
]
}
,{"automaticPlay":false,
"hyperlinks":[]
,
"eventInitialStates":[{"opacity":1,
"affineTransform":[1,0,0,1,0,0]
,
"texture":"s18.b",
"hidden":0}
,{"opacity":1,
"affineTransform":[1,0,0,1,0,0]
,
"texture":"s18.a",
"hidden":0}
]
,
"eventAnimations":[{"effect":"none",
"actions":[{"beginTime":0,
"from":{"scalar":1}
,
"action":"hidden",
"texture":"s18.a",
"to":{"scalar":1}
,
"timingFunction":"linear",
"duration":0.001}
]
,
"duration":0.001,
"animationType":"transition",
"beginTime":0,
"textures":["s18.a"]
}
,{"effect":"none",
"actions":[{"beginTime":0,
"from":{"scalar":0}
,
"action":"hidden",
"texture":"s18.b",
"to":{"scalar":0}
,
"timingFunction":"linear",
"duration":0.001}
]
,
"duration":0.001,
"animationType":"transition",
"beginTime":0,
"textures":["s18.b"]
}
]
,
"textRegions":[{"targetRectangle":{"y":68,
"width":810,
"x":107,
"height":96}
,
"text":"High Level Languages"}
,{"targetRectangle":{"y":309,
"width":636,
"x":164,
"height":88}
,
"text":"Compiled languages: C, C++, BASIC"}
,{"targetRectangle":{"y":397,
"width":688,
"x":164,
"height":134}
,
"text":"Interpreted JIT languages: Python, PHP, Ruby"}
,{"targetRectangle":{"y":531,
"width":643,
"x":164,
"height":46}
,
"text":"Bytecode languages: Java, C# (.NET)"}
]
}
,{"automaticPlay":false,
"hyperlinks":[]
,
"eventInitialStates":[{"opacity":1,
"affineTransform":[1,0,0,1,0,0]
,
"texture":"s19.b",
"hidden":0}
,{"opacity":1,
"affineTransform":[1,0,0,1,0,0]
,
"texture":"s19.a",
"hidden":0}
]
,
"eventAnimations":[{"effect":"none",
"actions":[{"beginTime":0,
"from":{"scalar":1}
,
"action":"hidden",
"texture":"s19.a",
"to":{"scalar":1}
,
"timingFunction":"linear",
"duration":0.001}
]
,
"duration":0.001,
"animationType":"transition",
"beginTime":0,
"textures":["s19.a"]
}
,{"effect":"none",
"actions":[{"beginTime":0,
"from":{"scalar":0}
,
"action":"hidden",
"texture":"s19.b",
"to":{"scalar":0}
,
"timingFunction":"linear",
"duration":0.001}
]
,
"duration":0.001,
"animationType":"transition",
"beginTime":0,
"textures":["s19.b"]
}
]
,
"textRegions":[{"targetRectangle":{"y":24,
"width":486,
"x":280,
"height":184}
,
"text":"Programming Paradigms"}
,{"targetRectangle":{"y":228,
"width":765,
"x":134,
"height":123}
,
"text":"Functional - A language that emphasizes consistency between executions. The same input should always produce the same output"}
,{"targetRectangle":{"y":350,
"width":763,
"x":134,
"height":123}
,
"text":"Imperative/Procedural - A collection of variables and functions (not the same as Functional) which runs in a top-down manner from beginning to end"}
,{"targetRectangle":{"y":472,
"width":786,
"x":134,
"height":93}
,
"text":"Object-oriented - Mimics real life, using objects that contain their own attributes and methods and communicate with other objects"}
,{"targetRectangle":{"y":564,
"width":769,
"x":134,
"height":94}
,
"text":"Logic - Flips the programming model on its head. Programmers define the solution constraints, and the program attempts to find all possible outputs for the input within those constraints"}
]
}
,{"automaticPlay":false,
"hyperlinks":[]
,
"eventInitialStates":[{"opacity":1,
"affineTransform":[1,0,0,1,0,0]
,
"texture":"s20.b",
"hidden":0}
,{"opacity":1,
"affineTransform":[1,0,0,1,0,0]
,
"texture":"s20.a",
"hidden":0}
]
,
"eventAnimations":[{"effect":"none",
"actions":[{"beginTime":0,
"from":{"scalar":1}
,
"action":"hidden",
"texture":"s20.a",
"to":{"scalar":1}
,
"timingFunction":"linear",
"duration":0.001}
]
,
"duration":0.001,
"animationType":"transition",
"beginTime":0,
"textures":["s20.a"]
}
,{"effect":"none",
"actions":[{"beginTime":0,
"from":{"scalar":0}
,
"action":"hidden",
"texture":"s20.b",
"to":{"scalar":0}
,
"timingFunction":"linear",
"duration":0.001}
]
,
"duration":0.001,
"animationType":"transition",
"beginTime":0,
"textures":["s20.b"]
}
]
,
"textRegions":[{"targetRectangle":{"y":24,
"width":781,
"x":132,
"height":184}
,
"text":"General Programming Process"}
,{"targetRectangle":{"y":244,
"width":526,
"x":134,
"height":88}
,
"text":"Design, Mock up, Pseudocode"}
,{"targetRectangle":{"y":332,
"width":697,
"x":134,
"height":88}
,
"text":"Write code, iterate design as needs arise"}
,{"targetRectangle":{"y":420,
"width":416,
"x":134,
"height":88}
,
"text":"Compile, test, debug, fix"}
,{"targetRectangle":{"y":508,
"width":648,
"x":134,
"height":88}
,
"text":"Refactor remaining code if time allows"}
,{"targetRectangle":{"y":596,
"width":431,
"x":134,
"height":46}
,
"text":"Documentation & training"}
]
}
,{"automaticPlay":false,
"hyperlinks":[]
,
"eventInitialStates":[{"opacity":1,
"affineTransform":[1,0,0,1,0,0]
,
"texture":"s21.b",
"hidden":0}
,{"opacity":1,
"affineTransform":[1,0,0,1,0,0]
,
"texture":"s21.a",
"hidden":0}
]
,
"eventAnimations":[{"effect":"none",
"actions":[{"beginTime":0,
"from":{"scalar":1}
,
"action":"hidden",
"texture":"s21.a",
"to":{"scalar":1}
,
"timingFunction":"linear",
"duration":0.001}
]
,
"duration":0.001,
"animationType":"transition",
"beginTime":0,
"textures":["s21.a"]
}
,{"effect":"none",
"actions":[{"beginTime":0,
"from":{"scalar":0}
,
"action":"hidden",
"texture":"s21.b",
"to":{"scalar":0}
,
"timingFunction":"linear",
"duration":0.001}
]
,
"duration":0.001,
"animationType":"transition",
"beginTime":0,
"textures":["s21.b"]
}
]
,
"textRegions":[{"targetRectangle":{"y":68,
"width":522,
"x":251,
"height":96}
,
"text":"The Sad News"}
,{"targetRectangle":{"y":307,
"width":743,
"x":134,
"height":134}
,
"text":"About 30% of programming involves actual coding. That's the best part! (Well, for me)"}
,{"targetRectangle":{"y":441,
"width":786,
"x":134,
"height":138}
,
"text":"The rest is interface/algorithm design, testing, debugging, documentation, meetings with fellow developers, etc. "}
]
}
,{"automaticPlay":false,
"hyperlinks":[]
,
"eventInitialStates":[{"opacity":1,
"affineTransform":[1,0,0,1,0,0]
,
"texture":"s22.b",
"hidden":0}
,{"opacity":1,
"affineTransform":[1,0,0,1,0,0]
,
"texture":"s22.a",
"hidden":0}
]
,
"eventAnimations":[{"effect":"none",
"actions":[{"beginTime":0,
"from":{"scalar":1}
,
"action":"hidden",
"texture":"s22.a",
"to":{"scalar":1}
,
"timingFunction":"linear",
"duration":0.001}
]
,
"duration":0.001,
"animationType":"transition",
"beginTime":0,
"textures":["s22.a"]
}
,{"effect":"none",
"actions":[{"beginTime":0,
"from":{"scalar":0}
,
"action":"hidden",
"texture":"s22.b",
"to":{"scalar":0}
,
"timingFunction":"linear",
"duration":0.001}
]
,
"duration":0.001,
"animationType":"transition",
"beginTime":0,
"textures":["s22.b"]
}
]
,
"textRegions":[{"targetRectangle":{"y":68,
"width":658,
"x":183,
"height":96}
,
"text":"Your First Program"}
,{"targetRectangle":{"y":282,
"width":219,
"x":134,
"height":73}
,
"text":"class Hello {"}
,{"targetRectangle":{"y":355,
"width":735,
"x":134,
"height":73}
,
"text":"\tpublic static void main(String[] args) {"}
,{"targetRectangle":{"y":428,
"width":680,
"x":134,
"height":73}
,
"text":"\t\tSystem.out.println(\"Hello World\");"}
,{"targetRectangle":{"y":501,
"width":79,
"x":134,
"height":73}
,
"text":"\t}"}
,{"targetRectangle":{"y":574,
"width":17,
"x":134,
"height":31}
,
"text":"}"}
]
}
,{"automaticPlay":false,
"hyperlinks":[]
,
"eventInitialStates":[{"opacity":1,
"affineTransform":[1,0,0,1,0,0]
,
"texture":"s23.b",
"hidden":0}
,{"opacity":1,
"affineTransform":[1,0,0,1,0,0]
,
"texture":"s23.a",
"hidden":0}
]
,
"eventAnimations":[{"effect":"none",
"actions":[{"beginTime":0,
"from":{"scalar":1}
,
"action":"hidden",
"texture":"s23.a",
"to":{"scalar":1}
,
"timingFunction":"linear",
"duration":0.001}
]
,
"duration":0.001,
"animationType":"transition",
"beginTime":0,
"textures":["s23.a"]
}
,{"effect":"none",
"actions":[{"beginTime":0,
"from":{"scalar":0}
,
"action":"hidden",
"texture":"s23.b",
"to":{"scalar":0}
,
"timingFunction":"linear",
"duration":0.001}
]
,
"duration":0.001,
"animationType":"transition",
"beginTime":0,
"textures":["s23.b"]
}
]
,
"textRegions":[{"targetRectangle":{"y":68,
"width":658,
"x":183,
"height":96}
,
"text":"Your First Program"}
,{"targetRectangle":{"y":236,
"width":782,
"x":134,
"height":229}
,
"text":"class Hello - The name of the “class” containing your program logic. The name of the file (Hello.java) is often the same name as the class"}
,{"targetRectangle":{"y":464,
"width":760,
"x":134,
"height":187}
,
"text":"{ } - Braces contain application logic. They are used to define “scope” which will be covered later. For now think of them as the beginning and end of what you are writing"}
]
}
,{"automaticPlay":false,
"hyperlinks":[]
,
"eventInitialStates":[{"opacity":1,
"affineTransform":[1,0,0,1,0,0]
,
"texture":"s24.b",
"hidden":0}
,{"opacity":1,
"affineTransform":[1,0,0,1,0,0]
,
"texture":"s24.a",
"hidden":0}
]
,
"eventAnimations":[{"effect":"none",
"actions":[{"beginTime":0,
"from":{"scalar":1}
,
"action":"hidden",
"texture":"s24.a",
"to":{"scalar":1}
,
"timingFunction":"linear",
"duration":0.001}
]
,
"duration":0.001,
"animationType":"transition",
"beginTime":0,
"textures":["s24.a"]
}
,{"effect":"none",
"actions":[{"beginTime":0,
"from":{"scalar":0}
,
"action":"hidden",
"texture":"s24.b",
"to":{"scalar":0}
,
"timingFunction":"linear",
"duration":0.001}
]
,
"duration":0.001,
"animationType":"transition",
"beginTime":0,
"textures":["s24.b"]
}
]
,
"textRegions":[{"targetRectangle":{"y":68,
"width":658,
"x":183,
"height":96}
,
"text":"Your First Program"}
,{"targetRectangle":{"y":223,
"width":509,
"x":134,
"height":53}
,
"text":"public static void main(String[] args)"}
,{"targetRectangle":{"y":275,
"width":746,
"x":134,
"height":83}
,
"text":"This line is written in all Java programs. It defines the entry point to the program, the first code to be executed."}
,{"targetRectangle":{"y":357,
"width":514,
"x":134,
"height":56}
,
"text":"public - Accessible by other parts of a program"}
,{"targetRectangle":{"y":412,
"width":516,
"x":134,
"height":56}
,
"text":"static - A class-level method. More on this later"}
,{"targetRectangle":{"y":467,
"width":769,
"x":134,
"height":85}
,
"text":"void - Nothing is ‘returned’ by this method. If a + b = c, then c would be what is normally returned."}
,{"targetRectangle":{"y":551,
"width":508,
"x":134,
"height":56}
,
"text":"main (Case-sensitive) - The name of the method"}
,{"targetRectangle":{"y":606,
"width":756,
"x":134,
"height":58}
,
"text":"String[] args - The first parameter to the program. Often used when executing a program from the command-prompt"}
]
}
,{"automaticPlay":false,
"hyperlinks":[]
,
"eventInitialStates":[{"opacity":1,
"affineTransform":[1,0,0,1,0,0]
,
"texture":"s25.b",
"hidden":0}
,{"opacity":1,
"affineTransform":[1,0,0,1,0,0]
,
"texture":"s25.a",
"hidden":0}
]
,
"eventAnimations":[{"effect":"none",
"actions":[{"beginTime":0,
"from":{"scalar":1}
,
"action":"hidden",
"texture":"s25.a",
"to":{"scalar":1}
,
"timingFunction":"linear",
"duration":0.001}
]
,
"duration":0.001,
"animationType":"transition",
"beginTime":0,
"textures":["s25.a"]
}
,{"effect":"none",
"actions":[{"beginTime":0,
"from":{"scalar":0}
,
"action":"hidden",
"texture":"s25.b",
"to":{"scalar":0}
,
"timingFunction":"linear",
"duration":0.001}
]
,
"duration":0.001,
"animationType":"transition",
"beginTime":0,
"textures":["s25.b"]
}
]
,
"textRegions":[{"targetRectangle":{"y":68,
"width":658,
"x":183,
"height":96}
,
"text":"Your First Program"}
,{"targetRectangle":{"y":227,
"width":544,
"x":134,
"height":62}
,
"text":"System.out.println(“Hello World”);"}
,{"targetRectangle":{"y":288,
"width":771,
"x":134,
"height":101}
,
"text":"System.out.println - The name of another method stored in the System package"}
,{"targetRectangle":{"y":388,
"width":743,
"x":134,
"height":102}
,
"text":"( ) - Placing parentheses after a method name will invoke that method"}
,{"targetRectangle":{"y":489,
"width":743,
"x":134,
"height":101}
,
"text":"“Hello World” - A string (sequence of characters) being sent as the first argument to the println method."}
,{"targetRectangle":{"y":589,
"width":777,
"x":134,
"height":71}
,
"text":"; - All commands in Java end with a semicolon. Note that {} brackets are excluded from this since they are not commands"}
]
}
,{"automaticPlay":false,
"hyperlinks":[]
,
"eventInitialStates":[{"opacity":1,
"affineTransform":[1,0,0,1,0,0]
,
"texture":"s26.b",
"hidden":0}
,{"opacity":1,
"affineTransform":[1,0,0,1,0,0]
,
"texture":"s26.a",
"hidden":0}
]
,
"eventAnimations":[{"effect":"none",
"actions":[{"beginTime":0,
"from":{"scalar":1}
,
"action":"hidden",
"texture":"s26.a",
"to":{"scalar":1}
,
"timingFunction":"linear",
"duration":0.001}
]
,
"duration":0.001,
"animationType":"transition",
"beginTime":0,
"textures":["s26.a"]
}
,{"effect":"none",
"actions":[{"beginTime":0,
"from":{"scalar":0}
,
"action":"hidden",
"texture":"s26.b",
"to":{"scalar":0}
,
"timingFunction":"linear",
"duration":0.001}
]
,
"duration":0.001,
"animationType":"transition",
"beginTime":0,
"textures":["s26.b"]
}
]
,
"textRegions":[{"targetRectangle":{"y":68,
"width":658,
"x":183,
"height":96}
,
"text":"Your First Program"}
,{"targetRectangle":{"y":230,
"width":720,
"x":134,
"height":127}
,
"text":"In the end, the Hello World program should print the words “Hello World” to the screen"}
,{"targetRectangle":{"y":356,
"width":743,
"x":134,
"height":214}
,
"text":"This program is particularly famous. It is a common practice for old and new programmers to try creating a “Hello World” program when introduced to a new language"}
,{"targetRectangle":{"y":569,
"width":773,
"x":134,
"height":87}
,
"text":"Of course since Java is a high-level language, it must be compiled before we can run it"}
]
}
,{"automaticPlay":false,
"hyperlinks":[]
,
"eventInitialStates":[{"opacity":1,
"affineTransform":[1,0,0,1,0,0]
,
"texture":"s27.b",
"hidden":0}
,{"opacity":1,
"affineTransform":[1,0,0,1,0,0]
,
"texture":"s27.a",
"hidden":0}
]
,
"eventAnimations":[{"effect":"none",
"actions":[{"beginTime":0,
"from":{"scalar":1}
,
"action":"hidden",
"texture":"s27.a",
"to":{"scalar":1}
,
"timingFunction":"linear",
"duration":0.001}
]
,
"duration":0.001,
"animationType":"transition",
"beginTime":0,
"textures":["s27.a"]
}
,{"effect":"none",
"actions":[{"beginTime":0,
"from":{"scalar":0}
,
"action":"hidden",
"texture":"s27.b",
"to":{"scalar":0}
,
"timingFunction":"linear",
"duration":0.001}
]
,
"duration":0.001,
"animationType":"transition",
"beginTime":0,
"textures":["s27.b"]
}
]
,
"textRegions":[{"targetRectangle":{"y":24,
"width":628,
"x":209,
"height":184}
,
"text":"Compiling A Java Program"}
,{"targetRectangle":{"y":227,
"width":674,
"x":134,
"height":92}
,
"text":"Open a terminal or command prompt. On the classroom machines you can use the Windows Powershell"}
,{"targetRectangle":{"y":318,
"width":765,
"x":134,
"height":94}
,
"text":"Navigate to the directory of your stored “Hello.java” file using cd and ls/dir"}
,{"targetRectangle":{"y":411,
"width":746,
"x":134,
"height":94}
,
"text":"Run the Java compiler on the file using “javac Hello.java”\u2028This will generate a compiled class file, “Hello.class”"}
,{"targetRectangle":{"y":504,
"width":719,
"x":134,
"height":93}
,
"text":"Run this class file using “java Hello” (note the missing file extension)"}
,{"targetRectangle":{"y":596,
"width":761,
"x":134,
"height":63}
,
"text":"You should see the words “Hello World” output to the command prompt"}
]
}
,{"automaticPlay":false,
"hyperlinks":[]
,
"eventInitialStates":[{"opacity":1,
"affineTransform":[1,0,0,1,0,0]
,
"texture":"s28.b",
"hidden":0}
,{"opacity":1,
"affineTransform":[1,0,0,1,0,0]
,
"texture":"s28.a",
"hidden":0}
]
,
"eventAnimations":[{"effect":"none",
"actions":[{"beginTime":0,
"from":{"scalar":1}
,
"action":"hidden",
"texture":"s28.a",
"to":{"scalar":1}
,
"timingFunction":"linear",
"duration":0.001}
]
,
"duration":0.001,
"animationType":"transition",
"beginTime":0,
"textures":["s28.a"]
}
,{"effect":"none",
"actions":[{"beginTime":0,
"from":{"scalar":0}
,
"action":"hidden",
"texture":"s28.b",
"to":{"scalar":0}
,
"timingFunction":"linear",
"duration":0.001}
]
,
"duration":0.001,
"animationType":"transition",
"beginTime":0,
"textures":["s28.b"]
}
]
,
"textRegions":[{"targetRectangle":{"y":24,
"width":628,
"x":209,
"height":184}
,
"text":"Compiling A Java Program"}
,{"targetRectangle":{"y":223,
"width":746,
"x":134,
"height":146}
,
"text":"When we get to the point of working with larger programs, this command-line compiling method will  become a burden"}
,{"targetRectangle":{"y":368,
"width":786,
"x":134,
"height":184}
,
"text":"You are expected to know how to compile from the command-line, but soon I we will switch to an Integrated Development Environment (IDE) to ease this compilation process"}
,{"targetRectangle":{"y":551,
"width":786,
"x":134,
"height":112}
,
"text":"If you prefer, you may use any Java IDE that you like provided that you ask me first. The class will be taught using NetBeans but Eclipse is another very popular IDE"}
]
}
,{"automaticPlay":false,
"hyperlinks":[{"url":"http://uaa.ryannixon.com/cs201",
"targetRectangle":{"y":533,
"width":536,
"x":134,
"height":46}
}
]
,
"eventInitialStates":[{"opacity":1,
"affineTransform":[1,0,0,1,0,0]
,
"texture":"s29.b",
"hidden":0}
,{"opacity":1,
"affineTransform":[1,0,0,1,0,0]
,
"texture":"s29.a",
"hidden":0}
]
,
"eventAnimations":[{"effect":"none",
"actions":[{"beginTime":0,
"from":{"scalar":1}
,
"action":"hidden",
"texture":"s29.a",
"to":{"scalar":1}
,
"timingFunction":"linear",
"duration":0.001}
]
,
"duration":0.001,
"animationType":"transition",
"beginTime":0,
"textures":["s29.a"]
}
,{"effect":"none",
"actions":[{"beginTime":0,
"from":{"scalar":0}
,
"action":"hidden",
"texture":"s29.b",
"to":{"scalar":0}
,
"timingFunction":"linear",
"duration":0.001}
]
,
"duration":0.001,
"animationType":"transition",
"beginTime":0,
"textures":["s29.b"]
}
]
,
"textRegions":[{"targetRectangle":{"y":68,
"width":402,
"x":311,
"height":96}
,
"text":"Questions?"}
,{"targetRectangle":{"y":307,
"width":707,
"x":134,
"height":134}
,
"text":"Please remember to look over the course syllabus and schedule"}
,{"targetRectangle":{"y":441,
"width":786,
"x":134,
"height":138}
,
"text":"A link will be on Blackboard as soon as I have access but in the meantime you may use:\u2028http://uaa.ryannixon.com/cs201"}
]
}
]
,
"loopSlideshow":0,
"showMode":0,
"majorVersion":0,
"notes":{}
,
"creator":"Apple Keynote 5.3",
"author":"",
"comment":"",
"pageCount":29,
"scalefactor480":0.3310547,
"slideCount":29}
